pyairtable/__init__.py
pyairtable/cli.py
pyairtable/exceptions.py
pyairtable/formulas.py
pyairtable/py.typed
pyairtable/testing.py
pyairtable/utils.py
pyairtable/api/__init__.py
pyairtable/api/api.py
pyairtable/api/base.py
pyairtable/api/enterprise.py
pyairtable/api/params.py
pyairtable/api/retrying.py
pyairtable/api/table.py
pyairtable/api/types.py
pyairtable/api/workspace.py
pyairtable/models/__init__.py
pyairtable/models/_base.py
pyairtable/models/audit.py
pyairtable/models/collaborator.py
pyairtable/models/comment.py
pyairtable/models/schema.py
pyairtable/models/webhook.py
pyairtable/orm/__init__.py
pyairtable/orm/fields.py
pyairtable/orm/generate.py
pyairtable/orm/lists.py
pyairtable/orm/model.py
pyairtable-3.1.0.dist-info/licenses/LICENSE
pyairtable-3.1.0.dist-info/METADATA
pyairtable-3.1.0.dist-info/WHEEL
pyairtable-3.1.0.dist-info/entry_points.txt
pyairtable-3.1.0.dist-info/top_level.txt
pyairtable-3.1.0.dist-info/RECORD
