Metadata-Version: 2.4
Name: pyairtable
Version: 3.1.0
Summary: Python Client for the Airtable API
Home-page: https://github.com/gtalarico/pyairtable
Author: Gui Talarico
License: MIT
Keywords: airtable,api,client,pyairtable
Classifier: Intended Audience :: Developers
Classifier: License :: OSI Approved :: MIT License
Classifier: Programming Language :: Python
Classifier: Programming Language :: Python :: 3.9
Classifier: Programming Language :: Python :: 3.10
Classifier: Programming Language :: Python :: 3.11
Classifier: Programming Language :: Python :: 3.12
Classifier: Programming Language :: Python :: 3.13
Classifier: Programming Language :: Python :: Implementation :: CPython
Classifier: Topic :: Software Development
License-File: LICENSE
Requires-Dist: inflection
Requires-Dist: pydantic<3,>=2
Requires-Dist: requests>=2.22.0
Requires-Dist: typing_extensions
Requires-Dist: urllib3>=1.26
Provides-Extra: cli
Requires-Dist: click; extra == "cli"
Dynamic: license-file
